{
  "about":{
    "name":"Devtrack",
    "author":"Jon Ross",
    "designer":"Jon Ross",
    "description":"A test railway for debugging"
  },
  "environment":{
    "skydome":"skydome.png"
  },
  "root":{
    "master":{
      "position":[-50,-20],
      "elevation":1,
      "gauge":1.435,
      "segments":[
        {
          "type":"straight",
          "length":100,
          "cant":0
        },
        {
          "type":"straight",
          "length":50,
          "cant":[0,2]
        },
        {
          "type":"curve",
          "arc":10,
          "radius":1200,
          "cant":[2,4]
        },
        {
          "type":"curve",
          "arc":10,
          "radius":220,
          "cant":[4,5]
        },
        {
          "type":"curve",
          "arc":50,
          "radius":120,
          "cant":5
        },
        {
          "type":"curve",
          "arc":10,
          "radius":220,
          "cant":[5,4]
        },
        {
          "type":"curve",
          "arc":10,
          "radius":1200,
          "cant":[4,2]
        },
        {
          "type":"straight",
          "length":50,
          "cant":[2,0]
        },
        {
          "type":"straight",
          "length":100,
          "cant":0
        },
        {
          "type":"straight",
          "length":50,
          "cant":[0,2]
        },
        {
          "type":"curve",
          "arc":10,
          "radius":1200,
          "cant":[2,4]
        },
        {
          "type":"curve",
          "arc":10,
          "radius":220,
          "cant":[4,5]
        },
        {
          "type":"curve",
          "arc":50,
          "radius":120,
          "cant":5
        },
        {
          "type":"curve",
          "arc":10,
          "radius":220,
          "cant":[5,4]
        },
        {
          "type":"curve",
          "arc":10,
          "radius":1200,
          "cant":[4,2]
        },
        {
          "type":"straight",
          "length":50,
          "cant":[2,0]
        },
        {
          "type":"straight",
          "length":100,
          "cant":0
        },
        {
          "type":"straight",
          "length":50,
          "cant":[0,2]
        },
        {
          "type":"curve",
          "arc":10,
          "radius":1200,
          "cant":[2,4]
        },
        {
          "type":"curve",
          "arc":10,
          "radius":220,
          "cant":[4,5]
        },
        {
          "type":"curve",
          "arc":50,
          "radius":120,
          "cant":5
        },
        {
          "type":"curve",
          "arc":10,
          "radius":220,
          "cant":[5,4]
        },
        {
          "type":"curve",
          "arc":10,
          "radius":1200,
          "cant":[4,2]
        },
        {
          "type":"straight",
          "length":50,
          "cant":[2,0]
        },
        {
          "type":"straight",
          "length":100,
          "cant":0
        },
        {
          "type":"straight",
          "length":50,
          "cant":[0,2]
        },
        {
          "type":"curve",
          "arc":10,
          "radius":1200,
          "cant":[2,4]
        },
        {
          "type":"curve",
          "arc":10,
          "radius":220,
          "cant":[4,5]
        },
        {
          "type":"curve",
          "arc":50,
          "radius":120,
          "cant":5
        },
        {
          "type":"curve",
          "arc":10,
          "radius":220,
          "cant":[5,4]
        },
        {
          "type":"curve",
          "arc":10,
          "radius":1200,
          "cant":[4,2]
        },
        {
          "type":"straight",
          "length":50,
          "cant":[2,0]
        }
      ]
    }
  }
}
